claude_swap/__init__.py
claude_swap/__main__.py
claude_swap/cli.py
claude_swap/exceptions.py
claude_swap/locking.py
claude_swap/logging_config.py
claude_swap/models.py
claude_swap/switcher.py
claude_swap-0.3.2.dist-info/METADATA
claude_swap-0.3.2.dist-info/WHEEL
claude_swap-0.3.2.dist-info/entry_points.txt
claude_swap-0.3.2.dist-info/RECORD
