Metadata-Version: 2.4
Name: claude-swap
Version: 0.3.2
Summary: Multi-account switcher for Claude Code
Project-URL: Homepage, https://github.com/realiti4/claude-swap
Project-URL: Repository, https://github.com/realiti4/claude-swap
Project-URL: Issues, https://github.com/realiti4/claude-swap/issues
Author-email: Onur Cetinkol <onurcetinkol@gmail.com>
License: MIT
Keywords: account-switcher,claude,claude-code,cli
Classifier: Development Status :: 4 - Beta
Classifier: Environment :: Console
Classifier: Intended Audience :: Developers
Classifier: License :: OSI Approved :: MIT License
Classifier: Operating System :: MacOS
Classifier: Operating System :: Microsoft :: Windows
Classifier: Operating System :: POSIX :: Linux
Classifier: Programming Language :: Python :: 3
Classifier: Programming Language :: Python :: 3.12
Classifier: Programming Language :: Python :: 3.13
Classifier: Programming Language :: Python :: 3.14
Classifier: Topic :: Utilities
Requires-Python: >=3.12
Requires-Dist: keyring>=25.0.0
